anguis/__init__.py
anguis/base.py
anguis/etcd.py
anguis/fs.py
anguis/gdrive.py
anguis/git.py
anguis/git_.py
anguis/memcached.py
anguis/memchached.py
anguis/redis.py
anguis/redis_.py
anguis/s3.py
anguis/sftp.py
anguis/sqlite.py
anguis-0.3.7.dist-info/AUTHORS.rst
anguis-0.3.7.dist-info/LICENSE
anguis-0.3.7.dist-info/METADATA
anguis-0.3.7.dist-info/WHEEL
anguis-0.3.7.dist-info/top_level.txt
anguis-0.3.7.dist-info/RECORD
