Metadata-Version: 2.1
Name: anguis
Version: 0.3.7
Summary: A generic key-store library.
Home-page: https://github.com/reale/anguis
Author: Roberto Reale
Author-email: roberto@reale.me
License: MIT license
Keywords: anguis,cache,key-value store
Platform: UNKNOWN
Classifier: Development Status :: 2 - Pre-Alpha
Classifier: Intended Audience :: Developers
Classifier: License :: OSI Approved :: MIT License
Classifier: Natural Language :: English
Classifier: Programming Language :: Python :: 3
Classifier: Programming Language :: Python :: 3.5
Classifier: Programming Language :: Python :: 3.6
Classifier: Programming Language :: Python :: 3.7
Requires-Python: >=3.5
Requires-Dist: gitpython
Requires-Dist: paramiko
Requires-Dist: etcd3
Requires-Dist: redis
Requires-Dist: bucketstore
Requires-Dist: sqlitedict
Requires-Dist: pymemcache
Requires-Dist: google-api-python-client
Requires-Dist: google-auth-httplib2
Requires-Dist: google-auth-oauthlib
